Metadata-Version: 1.0
Name: pyplanet-agones
Version: 0.2.3
Summary: Connects PyPlanet with Agones
Home-page: https://github.com/LudusMatchMaking/pyplanet_agones
Author: Jonathan Hertz
Author-email: jonathan_hertz2@live.dk
License: MIT
Platform: UNKNOWN
